Metadata-Version: 2.4
Name: dicom_wsi
Version: 1.0.5
Summary: Package for converting whole slide image files to dicom.
Home-page: https://github.com/Steven-N-Hart/dicom_wsi
Author: Steven N. Hart
Author-email: hart.steven@mayo.edu
License: MIT license
Keywords: dicom_wsi
Classifier: Development Status :: 3 - Alpha
Classifier: Intended Audience :: Developers
Classifier: Topic :: Software Development :: Build Tools
Classifier: License :: OSI Approved :: MIT License
Classifier: Programming Language :: Python :: 3
Classifier: Programming Language :: Python :: 3.5
Classifier: Programming Language :: Python :: 3.6
Classifier: Programming Language :: Python :: 3.7
Requires-Python: >=3
License-File: LICENSE
License-File: AUTHORS.rst
Requires-Dist: pyvips
Requires-Dist: pydicom
Requires-Dist: PyYAML
Requires-Dist: numpy
Requires-Dist: Pillow
Requires-Dist: tifffile
Requires-Dist: tiffile
Requires-Dist: datetime
Requires-Dist: openslide-python
Requires-Dist: cython
Requires-Dist: pylibjpeg
Requires-Dist: pylibjpeg-libjpeg
Requires-Dist: pylibjpeg-openjpeg
Requires-Dist: pytest
Dynamic: author
Dynamic: author-email
Dynamic: classifier
Dynamic: description
Dynamic: home-page
Dynamic: keywords
Dynamic: license
Dynamic: license-file
Dynamic: requires-dist
Dynamic: requires-python
Dynamic: summary
